CHANGES.txt
DEPENDENCES.txt
README.txt
setup.py
design/banner/banner_iig.gif
design/banner/banner_iigfs.gif
design/banner/banner_mosgird.gif
design/banner/banner_thebot_blue.png
design/banner/banner_thebot_green.png
design/banner/banner_thebot_orange.png
design/banner/banner_thedream_whiteblue.png
design/banner/banner_thedream_whitegreen.png
design/banner/banner_therream_orange.gif
design/banner/banner_zope.gif
design/banner/thebot.xcf.bz2
design/banner/thefream.xcf.bz2
design/html/arrow-left.png
design/html/arrow-right.png
design/html/arrow-up.png
design/html/bottomdreambot.png
design/html/enter.png
design/html/index.html
design/html/login.png
design/html/ok.png
design/html/robo.png
design/html/search.png
design/html/style.css
design/html/topdreambot.png
design/logo/robo.png
design/logo/robo2.png
design/logo/sekira.png
design/page/dreambot.png
design/page/eaglenest.png
design/page/zopelada.png
design/page/PSD/dreambot.psd.bz2
design/page/PSD/eaglenest.psd.bz2
design/page/PSD/zopelada.psd.bz2
design/page/XCF/dreambot.xcf.bz2
src/ng/__init__.py
src/ng.skin.base.egg-info/PKG-INFO
src/ng.skin.base.egg-info/SOURCES.txt
src/ng.skin.base.egg-info/dependency_links.txt
src/ng.skin.base.egg-info/namespace_packages.txt
src/ng.skin.base.egg-info/not-zip-safe
src/ng.skin.base.egg-info/requires.txt
src/ng.skin.base.egg-info/top_level.txt
src/ng/skin/__init__.py
src/ng/skin/base/__init__.py
src/ng/skin/base/configure-comment.zcml
src/ng/skin/base/configure-profile.zcml
src/ng/skin/base/configure-remotefs.zcml
src/ng/skin/base/configure-rubricator.zcml
src/ng/skin/base/configure.zcml
src/ng/skin/base/interfaces.py
src/ng/skin/base/maintemplate.pt
src/ng/skin/base/ng.skin.base.macros.txt
src/ng/skin/base/ng.skin.base.txt
src/ng/skin/base/orderinformation.py
src/ng/skin/base/skeleton.pt
src/ng/skin/base/style.css
src/ng/skin/base/style_form.css
src/ng/skin/base/style_ie.css
src/ng/skin/base/style_print.css
src/ng/skin/base/style_rest.css
src/ng/skin/base/style_text.css
src/ng/skin/base/adapter/__init__.py
src/ng/skin/base/adapter/configure.zcml
src/ng/skin/base/adapter/viewmain/__init__.py
src/ng/skin/base/adapter/viewmain/configure.zcml
src/ng/skin/base/adapter/viewmain/main.py
src/ng/skin/base/adapter/viewnextprev/__init__.py
