Metadata-Version: 1.0
Name: ng.skin.base
Version: 0.2.3
Summary: Our basic skin: some macros, adapters and so on
Home-page: http://www.dreambot.ru/dreambotsite/ng.skin.base/
Author: Andrey Orlov
Author-email: dbdt@dreambot.ru
License: GPL v2.1
Platform: UNKNOWN
Classifier: Environment :: Web Environment
Classifier: Intended Audience :: Developers
Classifier: License :: OSI Approved :: GNU General Public License (GPL)
Classifier: Programming Language :: Python
Classifier: Operating System :: OS Independent
Classifier: Topic :: Internet :: WWW/HTTP
Classifier: Framework :: Zope3
